[
  {
    "type": "sql_injection",
    "pattern": "union select",
    "severity": "high"
  },
  {
    "type": "sql_injection",
    "pattern": "' or 1=1",
    "severity": "high"
  },
  {
    "type": "xss",
    "pattern": "<script>",
    "severity": "high"
  },
  {
    "type": "xss",
    "pattern": "javascript:",
    "severity": "medium"
  },
  {
    "type": "directory_traversal",
    "pattern": "../",
    "severity": "high"
  },
  {
    "type": "admin_probe",
    "pattern": "/admin",
    "severity": "medium"
  },
  {
  "type": "scanner",
  "pattern": "scanner",
  "severity": "medium"
  }
]
